odoo/addons/base_order_by_related/README.rst
odoo/addons/base_order_by_related/__init__.py
odoo/addons/base_order_by_related/__manifest__.py
odoo/addons/base_order_by_related/i18n/base_order_by_related.pot
odoo/addons/base_order_by_related/i18n/it.po
odoo/addons/base_order_by_related/models/__init__.py
odoo/addons/base_order_by_related/models/models.py
odoo/addons/base_order_by_related/readme/CONTRIBUTORS.rst
odoo/addons/base_order_by_related/readme/DESCRIPTION.rst
odoo/addons/base_order_by_related/readme/USAGE.rst
odoo/addons/base_order_by_related/static/description/icon.png
odoo/addons/base_order_by_related/static/description/index.html
odoo/addons/base_order_by_related/tests/__init__.py
odoo/addons/base_order_by_related/tests/fake_models.py
odoo/addons/base_order_by_related/tests/test_order_by_related.py
odoo14_addon_base_order_by_related-14.0.1.0.1.dev5.dist-info/METADATA
odoo14_addon_base_order_by_related-14.0.1.0.1.dev5.dist-info/WHEEL
odoo14_addon_base_order_by_related-14.0.1.0.1.dev5.dist-info/top_level.txt
odoo14_addon_base_order_by_related-14.0.1.0.1.dev5.dist-info/RECORD
